invoice_generator/__init__.py
invoice_generator/generator.py
invoice_generator_varun2909-0.0.1.dist-info/METADATA
invoice_generator_varun2909-0.0.1.dist-info/WHEEL
invoice_generator_varun2909-0.0.1.dist-info/top_level.txt
invoice_generator_varun2909-0.0.1.dist-info/RECORD
