Metadata-Version: 2.1
Name: invoice_generator_varun2909
Version: 0.0.1
Summary: custom package to create invoice
Home-page: https://github.com/pypa/sampleproject
Author: Varun Gampa
Author-email: varunkumargampa7@gmail.com
Classifier: Programming Language :: Python :: 3
Classifier: License :: OSI Approved :: MIT License
Classifier: Operating System :: OS Independent
Requires-Python: >=3.6
Requires-Dist: reportlab
Requires-Dist: boto3
